setup.py
itick_dist/Binomialdistribution.py
itick_dist/Gaussiandistribution.py
itick_dist/Generaldistribution.py
itick_dist/__init__.py
itick_dist.egg-info/PKG-INFO
itick_dist.egg-info/SOURCES.txt
itick_dist.egg-info/dependency_links.txt
itick_dist.egg-info/not-zip-safe
itick_dist.egg-info/top_level.txt