Metadata-Version: 1.0
Name: itick-dist
Version: 0.1
Summary: Gaussian distributions
Home-page: UNKNOWN
Author: Aitik Dandapat
Author-email: aitik2000@gmail.com
License: UNKNOWN
Platform: UNKNOWN
